impresso/__init__.py
impresso/api_client/__init__.py
impresso/api_client/api/__init__.py
impresso/api_client/api/authentication/__init__.py
impresso/api_client/api/authentication/authentication_issue_token.py
impresso/api_client/api/collections/__init__.py
impresso/api_client/api/collections/create_collection.py
impresso/api_client/api/collections/find_collections.py
impresso/api_client/api/collections/get_collection.py
impresso/api_client/api/collections/patch_collections_collection_id_items.py
impresso/api_client/api/collections/remove_collection.py
impresso/api_client/api/collections/update_collection.py
impresso/api_client/api/content_items/__init__.py
impresso/api_client/api/content_items/get_content_item.py
impresso/api_client/api/entities/__init__.py
impresso/api_client/api/entities/find_entities.py
impresso/api_client/api/entities/get_entity.py
impresso/api_client/api/images/__init__.py
impresso/api_client/api/images/find_images.py
impresso/api_client/api/images/get_image.py
impresso/api_client/api/media_sources/__init__.py
impresso/api_client/api/media_sources/find_media_sources.py
impresso/api_client/api/media_sources/get_media_source.py
impresso/api_client/api/not_used/__init__.py
impresso/api_client/api/not_used/patch_collections_collection_id_items_id.py
impresso/api_client/api/search/__init__.py
impresso/api_client/api/search/search.py
impresso/api_client/api/search_facets/__init__.py
impresso/api_client/api/search_facets/get_images_facet.py
impresso/api_client/api/search_facets/get_search_facet.py
impresso/api_client/api/search_facets/get_tr_clusters_facet.py
impresso/api_client/api/search_facets/get_tr_passages_facet.py
impresso/api_client/api/text_reuse_clusters/__init__.py
impresso/api_client/api/text_reuse_clusters/find_text_reuse_clusters.py
impresso/api_client/api/text_reuse_clusters/get_text_reuse_cluster.py
impresso/api_client/api/text_reuse_passages/__init__.py
impresso/api_client/api/text_reuse_passages/find_text_reuse_passages.py
impresso-0.9.13.dist-info/LICENSE
impresso-0.9.13.dist-info/METADATA
impresso-0.9.13.dist-info/WHEEL
impresso-0.9.13.dist-info/entry_points.txt
impresso-0.9.13.dist-info/RECORD
