Metadata-Version: 2.1
Name: impresso
Version: 0.9.13
Summary: A Library to interact with the Impresso API
Home-page: https://github.com/impresso/impresso-py
License: AGPL-3.0-or-later
Author: Daniele Guido
Author-email: daniele.guido@uni.lu
Requires-Python: >=3.10.0,<4.0.0
Classifier: Intended Audience :: Developers
Classifier: Intended Audience :: Science/Research
Classifier: License :: OSI Approved :: GNU Affero General Public License v3 or later (AGPLv3+)
Classifier: Operating System :: OS Independent
Classifier: Programming Language :: Python :: 3
Classifier: Programming Language :: Python :: 3.10
Classifier: Programming Language :: Python :: 3.11
Classifier: Programming Language :: Python :: 3 :: Only
Requires-Dist: PyJWT (>=2.8.0,<3.0.0)
Requires-Dist: PyYAML (>=6.0.2,<7.0.0)
Requires-Dist: attrs (>=23.2.0,<24.0.0)
Requires-Dist: httpx (>=0.27.0,<0.28.0)
Requires-Dist: matplotlib (>=3.7.0,<4.0.0)
Requires-Dist: pandas (>=2.1.0,<3.0.0)
Requires-Dist: pandas-stubs (>=2.2.1.240316,<3.0.0.0)
Requires-Dist: protobuf (>=4.25.0,<5.0.0)
Requires-Dist: pydantic (>=2.6.4,<3.0.0)
Requires-Dist: python-dateutil (>=2.8.0,<3.0.0)
Requires-Dist: types-PyYAML (>=6.0.12.20240311,<7.0.0.0)
Requires-Dist: types-protobuf (>=5.27.0.20240626,<6.0.0.0)
Project-URL: Endpoint, https://impresso-project.ch/public-api/v1
Project-URL: Issues, https://github.com/impresso/impresso-py/issues
Project-URL: Repository, https://github.com/impresso/impresso-py
